eikonal/__init__.py
eikonal/data.py
eikonal/linear.py
eikonal/vis/__init__.py
eikonal/vis/ray.py
eikonal-2.0.1.dist-info/WHEEL
eikonal-2.0.1.dist-info/METADATA
eikonal-2.0.1.dist-info/RECORD
