Metadata-Version: 2.1
Name: eikonal
Version: 2.0.1
Summary: 
Author: Your Name
Author-email: you@example.com
Requires-Python: >=3.8,<3.11
Classifier: Programming Language :: Python :: 3
Classifier: Programming Language :: Python :: 3.10
Classifier: Programming Language :: Python :: 3.8
Classifier: Programming Language :: Python :: 3.9
Requires-Dist: numpy (>=1.22.3,<2.0.0)
Requires-Dist: scipy (>=1.8.0,<2.0.0)
